{
  "project_info": {
    "project_number": "117152979768",
    "project_id": "bhayangkara-chat",
    "storage_bucket": "bhayangkara-chat.appspot.com"
  },
  "client": [
    {
      "client_info": {
        "mobilesdk_app_id": "1:117152979768:android:4d30cc8839a2582bc93fcd",
        "android_client_info": {
          "package_name": "com.example.aplikasi_rs"
        }
      },
      "oauth_client": [
        {
          "client_id": "117152979768-mmuvcsqtr4fpvptpkmmjvblsc04sb2mm.apps.googleusercontent.com",
          "client_type": 3
        }
      ],
      "api_key": [
        {
          "current_key": "AIzaSyDM0rpulQcKiOqdNSW-_fkRl2JTHCzWRTI"
        }
      ],
      "services": {
        "appinvite_service": {
          "other_platform_oauth_client": [
            {
              "client_id": "117152979768-mmuvcsqtr4fpvptpkmmjvblsc04sb2mm.apps.googleusercontent.com",
              "client_type": 3
            }
          ]
        }
      }
    }
  ],
  "configuration_version": "1"
}